Workbook

Sheet Hypotheses
B2: Hypotheses et sources - PMS Hotel Makarim (Tetouan)
B4: Parametre | C4: Valeur | D4: Unite | E4: Source / justification
B5: Nombre de chambres | C5: 24 | D5: chambres | E5: Tripadvisor - Hotel Makarim Tetouan (24 chambres) : https://www.tripadvisor.com/Hotel_Review-g295397-d17789881-Reviews-Hotel_Makarim_Tetouan-Tetouan_Tanger_Tetouan_Al_Hoceima.html
B6: Taux d'occupation (TO) moyen 3 etoiles Maroc | C6: 0.63 | D6: % | E6: SiyahaMag, taux d'occupation hotels Maroc 2026 : https://siyahamag.ma/guide/taux-occupation-hotels-maroc-2026
B7: ADR (prix moyen/nuit) - hypothese retenue | C7: 600 | D7: MAD | E7: Milieu de la fourchette ADR 3 etoiles Maroc 350-750 MAD (SiyahaMag) et ADR effectif Makarim ~48-80 USD/nuit (momondo, HotelsCombined, Tripadvisor)
B8: Taux de change EUR -> MAD | C8: 10.7 | D8: MAD/EUR | E8: Xe.com, cours au 16/07/2026 : https://www.xe.com/fr/currencyconverter/convert/?Amount=1&From=EUR&To=MAD
B9: Taux de change USD -> MAD | C9: 9.35 | D9: MAD/USD | E9: Trading Economics, cours au 15/07/2026 : https://tradingeconomics.com/morocco/currency
B10: Commission Booking.com effective | C10: 0.18 | D10: % | E10: Bluerails / WeSpeak, commission effective 18-22% : https://www.bluerails.com/blog/the-20-percent-question
B11: Part des reservations via OTA (statu quo) | C11: 0.7 | D11: % | E11: Estimation pour petit hotel independant fortement depedant des OTA (a ajuster selon donnees reelles Makarim)
B12: Cout horaire charge personnel (estimation) | C12: 50 | D12: MAD/h | E12: Estimation cout charge personnel front-desk/hebergement au Maroc (a valider avec la comptabilite de l'hotel)
B13: Abonnement PMS SaaS (BUY) - base | C13: 150 | D13: USD/mois | E13: Milieu de fourchette PMS petites structures 50-300 USD/mois : https://www.hotelogix.com/blog/hotel-pms-pricing
B14: Frais de mise en oeuvre PMS SaaS (BUY, ponctuel) | C14: 5000 | D14: MAD | E14: Estimation reduite pour petite structure (ref. mise en oeuvre 2000-15000 EUR pour hotels plus grands) : https://neo-gest.fr/logiciel-reservation-hotel-comparatif-2026/
B15: Cout developpement initial (BUILD) - base | C15: 80000 | D15: MAD | E15: Milieu de fourchette outil metier standard 40000-150000 MAD : https://rmgsolutions.ma/fr/ressources/developpement-application-metier-maroc-guide-2026
B16: Taux de maintenance annuelle (BUILD) | C16: 0.15 | D16: % du cout dev | E16: Regle empirique 15-20%/an : https://rmgsolutions.ma/fr/ressources/developpement-application-metier-maroc-guide-2026
... B23: Hausse reservations directes (BUY) - points de % | C23: 0.1 | D23: points % | E23: Reservations directes +10-15% avec channel manager/booking engine : https://neo-gest.fr/logiciel-reservation-hotel-comparatif-2026/

Sheet Modele 3 ans
B2: Modelisation des revenus 3 ans - Statu quo vs Build vs Buy
B3: Hotel Makarim (24 chambres, Tetouan) - Unite : MAD sauf indication contraire. Toutes les cellules sont des formules liees a l'onglet Hypotheses.
B5: 1. STATU QUO - PMS actuel local, sans changement
B6: Poste | C6: An 1 | D6: An 2 | E6: An 3
B7: Nuits vendues (chambre-nuits) | C7: =Hypotheses!C5*365*Hypotheses!C6 -> 5518.8 | D7: =Hypotheses!C5*365*Hypotheses!C6 -> 5518.8 | E7: =Hypotheses!C5*365*Hypotheses!C6 -> 5518.8
B8: Revenu hebergement brut (MAD) | C8: =C7*Hypotheses!C7 -> 3311280 | D8: =D7*Hypotheses!C7 -> 3311280 | E8: =E7*Hypotheses!C7 -> 3311280
B9: Revenu via OTA (MAD) | C9: =C8*Hypotheses!C11 -> 2317896 | D9: =D8*Hypotheses!C11 -> 2317896 | E9: =E8*Hypotheses!C11 -> 2317896
B10: Commission Booking.com payee (MAD) | C10: =C9*Hypotheses!C10 -> 417221.28 | D10: =D9*Hypotheses!C10 -> 417221.28 | E10: =E9*Hypotheses!C10 -> 417221.28
B11: Cout PMS (MAD) | C11: 0 | D11: 0 | E11: 0
B12: Valeur temps economise (MAD) | C12: 0 | D12: 0 | E12: 0
B13: Benefice net operationnel (MAD) | C13: =C8-C10-C11+C12 -> 2894058.7 | D13: =D8-D10-D11+D12 -> 2894058.7 | E13: =E8-E10-E11+E12 -> 2894058.7
B15: 2. BUILD - Poursuivre le developpement interne (hebergement en ligne + automatisation Gmail/n8n)
B16: Poste | C16: An 1 | D16: An 2 | E16: An 3
B17: Nuits vendues (chambre-nuits) | C17: =C7 -> 5518.8 | D17: =D7 -> 5518.8 | E17: =E7 -> 5518.8
B18: Revenu hebergement brut (MAD) | C18: =C8*(1+Hypotheses!C20) -> 3377505.6 | D18: =D8*(1+Hypotheses!C20) -> 3377505.6 | E18: =E8*(1+Hypotheses!C20) -> 3377505.6
B19: Revenu via OTA (MAD) | C19: =C18*Hypotheses!C11 -> 2364253.9 | D19: =D18*Hypotheses!C11 -> 2364253.9 | E19: =E18*Hypotheses!C11 -> 2364253.9
B20: Commission Booking.com payee (MAD) | C20: =C19*Hypotheses!C10 -> 425565.71 | D20: =D19*Hypotheses!C10 -> 425565.71 | E20: =E19*Hypotheses!C10 -> 425565.71
B21: Cout PMS - dev + hebergement + maintenance (MAD) | C21: =Hypotheses!C15+Hypotheses!C17*12+Hypotheses!C18 -> 103880 | D21: =Hypotheses!C15*Hypotheses!C16+Hypotheses!C17*12+Hypotheses!C18 -> 35880 | E21: =Hypotheses!C15*Hypotheses!C16+Hypotheses!C17*12+Hypotheses!C18 -> 35880
B22: Valeur temps economise (MAD) | C22: =Hypotheses!C22*Hypotheses!C12 -> 12500 | D22: =Hypotheses!C22*Hypotheses!C12 -> 12500 | E22: =Hypotheses!C22*Hypotheses!C12 -> 12500
B23: Benefice net operationnel (MAD) | C23: =C18-C20-C21+C22 -> 2860559.9 | D23: =D18-D20-D21+D22 -> 2928559.9 | E23: =E18-E20-E21+E22 -> 2928559.9
B25: 3. BUY - Adopter un PMS SaaS commercial + channel manager
B26: Poste | C26: An 1 | D26: An 2 | E26: An 3
B27: Nuits vendues (chambre-nuits) | C27: =C7 -> 5518.8 | D27: =D7 -> 5518.8 | E27: =E7 -> 5518.8
B28: Revenu hebergement brut (MAD) | C28: =C8*(1+Hypotheses!C19) -> 3576182.4 | D28: =D8*(1+Hypotheses!C19) -> 3576182.4 | E28: =E8*(1+Hypotheses!C19) -> 3576182.4
B29: Part OTA apres hausse resas directes (%) | C29: =Hypotheses!C11-Hypotheses!C23 -> 0.6 | D29: =Hypotheses!C11-Hypotheses!C23 -> 0.6 | E29: =Hypotheses!C11-Hypotheses!C23 -> 0.6
B30: Revenu via OTA (MAD) | C30: =C28*C29 -> 2145709.4 | D30: =D28*D29 -> 2145709.4 | E30: =E28*E29 -> 2145709.4
B31: Commission Booking.com payee (MAD) | C31: =C30*Hypotheses!C10 -> 386227.7 | D31: =D30*Hypotheses!C10 -> 386227.7 | E31: =E30*Hypotheses!C10 -> 386227.7
B32: Cout PMS - abonnement + mise en oeuvre (MAD) | C32: =Hypotheses!C13*Hypotheses!C9*12+Hypotheses!C14 -> 21830 | D32: =Hypotheses!C13*Hypotheses!C9*12 -> 16830 | E32: =Hypotheses!C13*Hypotheses!C9*12 -> 16830
B33: Valeur temps economise (MAD) | C33: =Hypotheses!C21*Hypotheses!C12 -> 25000 | D33: =Hypotheses!C21*Hypotheses!C12 -> 25000 | E33: =Hypotheses!C21*Hypotheses!C12 -> 25000
B34: Benefice net operationnel (MAD) | C34: =C28-C31-C32+C33 -> 3193124.7 | D34: =D28-D31-D32+D33 -> 3198124.7 | E34: =E28-E31-E32+E33 -> 3198124.7
B36: 4. COMPARAISON - Benefice net operationnel par scenario
B37: Scenario | C37: An 1 | D37: An 2 | E37: An 3 | F37: Cumul 3 ans
B38: Statu quo | C38: =C13 -> 2894058.7 | D38: =D13 -> 2894058.7 | E38: =E13 -> 2894058.7 | F38: =SUM(C38:E38) -> 8682176.2
B39: Build (developpement interne) | C39: =C23 -> 2860559.9 | D39: =D23 -> 2928559.9 | E39: =E23 -> 2928559.9 | F39: =SUM(C39:E39) -> 8717679.7
B40: Buy (PMS SaaS commercial) | C40: =C34 -> 3193124.7 | D40: =D34 -> 3198124.7 | E40: =E34 -> 3198124.7 | F40: =SUM(C40:E40) -> 9589374.1
B42: Delta Build vs Statu quo | C42: =C39-C38 -> -33498.826 | D42: =D39-D38 -> 34501.174 | E42: =E39-E38 -> 34501.174 | F42: =F39-F38 -> 35503.523
B43: Delta Buy vs Statu quo | C43: =C40-C38 -> 299065.98 | D43: =D40-D38 -> 304065.98 | E43: =E40-E38 -> 304065.98 | F43: =F40-F38 -> 907197.94
B44: Delta Buy vs Build | C44: =C40-C39 -> 332564.81 | D44: =D40-D39 -> 269564.81 | E44: =E40-E39 -> 269564.81 | F44: =F40-F39 -> 871694.42

Sheet Sensibilite
B2: Analyse de sensibilite (An 1)
B4: 1. Scenario BUY - variation de l'uplift RevPAR
B5: Scenario | C5: Uplift RevPAR | D5: Revenu hebergement An1 | E5: Commission payee An1 | F5: Benefice net An1
B6: Pessimiste | C6: 0.05 | D6: ='Modele 3 ans'!C8*(1+C6) -> 3476844 | E6: =D6*(Hypotheses!C11-Hypotheses!C23)*Hypotheses!C10 -> 375499.15 | F6: =D6-E6-'Modele 3 ans'!C32+'Modele 3 ans'!C33 -> 3104514.8
B7: Base | C7: =Hypotheses!C19 -> 0.08 | D7: ='Modele 3 ans'!C8*(1+C7) -> 3576182.4 | E7: =D7*(Hypotheses!C11-Hypotheses!C23)*Hypotheses!C10 -> 386227.7 | F7: =D7-E7-'Modele 3 ans'!C32+'Modele 3 ans'!C33 -> 3193124.7
B8: Optimiste | C8: 0.15 | D8: ='Modele 3 ans'!C8*(1+C8) -> 3807972 | E8: =D8*(Hypotheses!C11-Hypotheses!C23)*Hypotheses!C10 -> 411260.98 | F8: =D8-E8-'Modele 3 ans'!C32+'Modele 3 ans'!C33 -> 3399881
B10: 2. Scenario BUILD - variation du cout de developpement initial
B11: Scenario | C11: Cout dev initial (MAD) | D11: Cout PMS An1 (MAD) | E11: Benefice net An1
B12: Pessimiste | C12: 150000 | D12: =C12+Hypotheses!C17*12+Hypotheses!C18 -> 173880 | E12: ='Modele 3 ans'!C18-'Modele 3 ans'!C20-D12+'Modele 3 ans'!C22 -> 2790559.9
B13: Base | C13: =Hypotheses!C15 -> 80000 | D13: =C13+Hypotheses!C17*12+Hypotheses!C18 -> 103880 | E13: ='Modele 3 ans'!C18-'Modele 3 ans'!C20-D13+'Modele 3 ans'!C22 -> 2860559.9
B14: Optimiste | C14: 40000 | D14: =C14+Hypotheses!C17*12+Hypotheses!C18 -> 63880 | E14: ='Modele 3 ans'!C18-'Modele 3 ans'!C20-D14+'Modele 3 ans'!C22 -> 2900559.9
B16: Note : le scenario Base reprend exactement les valeurs de l'onglet 'Modele 3 ans' (An 1). Les scenarios Pessimiste/Optimiste font varier un seul parametre a la fois, toutes choses egales par ailleurs.

Sheet Synthese
B2: Synthese - Comparaison 3 ans
B4: Scenario | C4: Benefice net cumule 3 ans (MAD) | D4: Delta vs Statu quo (MAD)
B5: Statu quo | C5: ='Modele 3 ans'!F38 -> 8682176.2 | D5: 0
B6: Build (developpement interne) | C6: ='Modele 3 ans'!F39 -> 8717679.7 | D6: =C6-C5 -> 35503.523
B7: Buy (PMS SaaS commercial) | C7: ='Modele 3 ans'!F40 -> 9589374.1 | D7: =C7-C5 -> 907197.94
B9: Scenario le plus favorable (benefice net cumule le plus eleve) | C9: =INDEX(B5:B7,MATCH(MAX(C5:C7),C5:C7,0)) -> Buy (PMS SaaS commercial)
B11: Rappel de lecture :
B12: - Statu quo = PMS local actuel, sans investissement, sans automatisation, sans channel manager.
B13: - Build = poursuite du developpement interne (hebergement en ligne + automatisation Gmail/n8n), sans synchronisation temps reel avec les OTA.
B14: - Buy = adoption d'un PMS SaaS commercial avec channel manager (synchronisation temps reel, risque d'overbooking quasi nul).
B15: - Toutes les hypotheses sont modifiables dans l'onglet Hypotheses ; les resultats se recalculent automatiquement.
